libsbmlnetwork/__init__.py
libsbmlnetwork/libsbmlnetwork.py
libsbmlnetwork/libs/libsbmlnetwork.0.5.12.dylib
libsbmlnetwork/libs/libsbmlnetwork.0.dylib
libsbmlnetwork/libs/libsbmlnetwork.dylib
libsbmlnetwork-0.5.12.dist-info/METADATA
libsbmlnetwork-0.5.12.dist-info/WHEEL
libsbmlnetwork-0.5.12.dist-info/top_level.txt
libsbmlnetwork-0.5.12.dist-info/RECORD
