Metadata-Version: 2.1
Name: libsbmlnetwork
Version: 0.5.12
Summary: LibSBML Network Python API
Home-page: https://github.com/adelhpour/libsmlNetwork
Author: Adel Heydarabadipour
Author-email: adelhp@uw.edu
License: MIT License
Keywords: SBML,Layout,Render
Platform: Windows
Platform: MacOS
Platform: Unix
Classifier: Intended Audience :: Science/Research
Classifier: Programming Language :: C++
Classifier: License :: OSI Approved :: MIT License
Classifier: Operating System :: Microsoft :: Windows
Classifier: Operating System :: MacOS :: MacOS X
Classifier: Operating System :: Unix
Requires-Python: >=3.8
